Metadata-Version: 2.1
Name: distri-probability-tests
Version: 1.1
Summary: Gaussian distributions
Home-page: UNKNOWN
Author: Miguel
Author-email: name@gmail.com
License: UNKNOWN
Platform: UNKNOWN
